LICENSE
MANIFEST.in
readme.md
requirements.txt
setup.cfg
setup.py
extractRegion/__init__.py
extractRegion/contigs.fasta
extractRegion/extractRegion.py
extractRegion/grab.fasta
extractRegion/multientry.fasta
extractRegion/regions.txt
extractRegion/test_extractRegion.py
fastaRenamers/__init__.py
fastaRenamers/aribaRenamer.py
fastaRenamers/prokkaToUniprotRenamer.py
fastaRenamers/spadesContigsRenamer.py
open_utils.egg-info/PKG-INFO
open_utils.egg-info/SOURCES.txt
open_utils.egg-info/dependency_links.txt
open_utils.egg-info/entry_points.txt
open_utils.egg-info/requires.txt
open_utils.egg-info/top_level.txt