Metadata-Version: 1.1
Name: open-utils
Version: 0.0.5
Summary: you didn't think you needed it til you did
Home-page: https://github.com/nickp60/EzClermont
Author: Nick Waters
Author-email: nickp60@gmail.com
License: MIT
Keywords: bioinformatics evolution genomics development
Platform: UNKNOWN
Classifier: Development Status :: 3 - Alpha
Classifier: Intended Audience :: Developers
Classifier: Intended Audience :: Science/Research
Classifier: Topic :: Scientific/Engineering :: Bio-Informatics
Classifier: License :: OSI Approved :: MIT License
Classifier: Programming Language :: Python :: 3.5
Classifier: Programming Language :: Python :: 3.6
